itar/__init__.py
itar/cli.py
itar/index.py
itar/indexed_tar_file.py
itar/py.typed
itar/utils.py
itar-0.4.2.dist-info/WHEEL
itar-0.4.2.dist-info/entry_points.txt
itar-0.4.2.dist-info/METADATA
itar-0.4.2.dist-info/RECORD
