Metadata-Version: 2.3
Name: itar
Version: 0.4.2
Summary: tar file index for constant-time member access
Author: Karim Abou Zeid
Author-email: Karim Abou Zeid <contact@ka.codes>
Requires-Dist: msgpack>=1.1.1
Requires-Dist: tqdm>=4.67.1
Requires-Dist: humanize>=4.12.3
Requires-Python: >=3.10
